datagen/__init__.py
datagen/api/__init__.py
datagen/api/assets.py
datagen/api/catalog/__init__.py
datagen/api/catalog/attributes.py
datagen/api/catalog/cache/backgrounds.json
datagen/api/catalog/cache/beards.json
datagen/api/catalog/cache/eyebrows.json
datagen/api/catalog/cache/eyes.json
datagen/api/catalog/cache/glasses.json
datagen/api/catalog/cache/hair.json
datagen/api/catalog/cache/hic/attributes.json
datagen/api/catalog/cache/hic/presets.json
datagen/api/catalog/cache/humans/attributes.json
datagen/api/catalog/cache/humans/defaults.json
datagen/api/catalog/cache/masks.json
datagen/api/catalog/containers.py
datagen/api/catalog/exceptions.py
datagen/api/catalog/hooks/__init__.py
datagen/api/catalog/hooks/hic.py
datagen/api/catalog/hooks/humans.py
datagen/api/catalog/impl.py
datagen/api/client/__init__.py
datagen/api/client/containers.py
datagen/api/client/exceptions.py
datagen/api/client/schemas.py
datagen/api/client/session.py
datagen/api/containers.py
datagen/api/datapoint/__init__.py
datagen/api/impl.py
datagen/api/requests/__init__.py
datagen/api/requests/datapoint/__init__.py
datagen/api/requests/datapoint/builder.py
datagen/api/requests/director.py
datagen/components/__init__.py
datagen/components/camera.py
datagen/components/datapoint/__init__.py
datagen/components/datapoint/container.py
datagen/components/datapoint/entity/__init__.py
datagen/components/datapoint/entity/base.py
datagen/components/datapoint/entity/hic.py
datagen/components/datapoint/entity/identities.py
datagen/components/datapoint/repo.py
datagen/components/dataset.py
datagen/components/datasource.py
datagen/components/scene.py
datagen/components/sequence.py
datagen/config/__init__.py
datagen/config/config.py
datagen/config/settings.toml
datagen/containers.py
datagen/core/__init__.py
datagen/core/tasks/__init__.py
datagen/core/tasks/containers.py
datagen/core/tasks/task.py
datagen/core/tasks/task_definitions.py
datagen/core/tasks/task_runner.py
datagen/dev/__init__.py
datagen_tech-1.10.6.dist-info/LICENSE
datagen_tech-1.10.6.dist-info/METADATA
datagen_tech-1.10.6.dist-info/WHEEL
datagen_tech-1.10.6.dist-info/RECORD
