Metadata-Version: 2.1
Name: datagen-tech
Version: 1.10.6
Summary: Datagen SDK
Home-page: https://gitlab.com/datagen1/core/sdk
Author: Datagen Technologies Ltd.
Requires-Python: >=3.8,<4.0
Classifier: Programming Language :: Python :: 3
Classifier: Programming Language :: Python :: 3.8
Classifier: Programming Language :: Python :: 3.9
Classifier: Programming Language :: Python :: 3.10
Classifier: Programming Language :: Python :: 3.11
Provides-Extra: camera-utils
Requires-Dist: aiofiles (>=23.1.0,<24.0.0)
Requires-Dist: aiohttp (>=3.8,<4.0)
Requires-Dist: appdirs (>=1.4,<2.0)
Requires-Dist: asyncio-channel (>=0.9.1,<0.10.0)
Requires-Dist: datagen-protocol-functional (==0.31.0)
Requires-Dist: dependency-injector (>4.6)
Requires-Dist: dynaconf (>=2.2.3,<3.0.0)
Requires-Dist: importlib-metadata (<5.0.0)
Requires-Dist: marshmallow-dataclass (>=6)
Requires-Dist: marshmallow-enum (>=1.5)
Requires-Dist: nest-asyncio (>=1.5.6,<2.0.0)
Requires-Dist: numpy (>=1.20,<2.0) ; python_version >= "3.8" and python_version < "3.9"
Requires-Dist: numpy (>=1.20,<2.0) ; python_version >= "3.9"
Requires-Dist: opencv-python (>=4.4,<5.0)
Requires-Dist: pandas (>=1.1,<2.0)
Requires-Dist: pydantic (>=1.9,<2.0)
Requires-Dist: requests (>=2.28.1,<3.0.0)
Requires-Dist: scipy (>=1.5,<2.0) ; (python_version < "3.9") and (extra == "camera-utils")
Requires-Dist: scipy (>=1.9,<2.0) ; (python_version >= "3.9" and python_version < "4.0") and (extra == "camera-utils")
Project-URL: Repository, https://gitlab.com/datagen1/core/sdk
